eesuhn_sdk/__init__.py
eesuhn_sdk/ansi.py
eesuhn_sdk/py.typed
eesuhn_sdk/utils.py
eesuhn_sdk-0.1.3.dist-info/LICENSE
eesuhn_sdk-0.1.3.dist-info/METADATA
eesuhn_sdk-0.1.3.dist-info/WHEEL
eesuhn_sdk-0.1.3.dist-info/top_level.txt
eesuhn_sdk-0.1.3.dist-info/RECORD
