Metadata-Version: 2.2
Name: eesuhn-sdk
Version: 0.1.3
Summary: eesuhn's Personal SDK
Home-page: https://github.com/eesuhn/eesuhn-sdk
Author: eesuhn
Author-email: eesuhn <eason.yihong@gmail.com>
Maintainer-email: eesuhn <eason.yihong@gmail.com>
License: MIT License
Project-URL: Homepage, https://github.com/eesuhn/eesuhn-sdk
Project-URL: Repository, https://github.com/eesuhn/eesuhn-sdk
Project-URL: Issues, https://github.com/eesuhn/eesuhn-sdk/issues
Keywords: eesuhn
Classifier: Development Status :: 3 - Alpha
Classifier: Intended Audience :: Developers
Classifier: Programming Language :: Python :: 3
Requires-Python: >=3.12
License-File: LICENSE
Dynamic: author
Dynamic: home-page
Dynamic: requires-python
